kaomi_server/__init__.py
kaomi_server/__main__.py
kaomi_server/config_file.py
kaomi_server/deployer.py
kaomi_server/example_files.py
kaomi_server/functions.py
kaomi_server/globals.py
kaomi_server/kaomi_server.py
kaomi_server/log.py
kaomi_server/views_actions.py
kaomi_server/views_alive.py
kaomi_server/views_files.py
kaomi_server-0.5.3.dist-info/METADATA
kaomi_server-0.5.3.dist-info/WHEEL
kaomi_server-0.5.3.dist-info/top_level.txt
kaomi_server-0.5.3.dist-info/RECORD
