Metadata-Version: 2.1
Name: kaomi-server
Version: 0.5.3
Summary: This package contains the server endpoint for the Kaomi deployer. Kaomi server has to be run on the system where you want to deploy.
Home-page: https://gitlab.linkspirit.it/linkspirit/kaomi-deployer.git
Author: Linkspirit Team
Author-email: tecnici@linkspirit.it
License: UNKNOWN
Platform: UNKNOWN
Classifier: Programming Language :: Python :: 3
Classifier: Operating System :: OS Independent
Requires-Python: >=3
Requires-Dist: cherrypy (>=18.0.0)
